HISTORY.txt
LICENSE
PKG-INFO
README.rst
setup.py
TermEmulator/TermEmulator.py
TermEmulator/TermEmulatorDemo.py
TermEmulator/__init__.py
TermEmulator.egg-info/PKG-INFO
TermEmulator.egg-info/SOURCES.txt
TermEmulator.egg-info/dependency_links.txt
TermEmulator.egg-info/entry_points.txt
TermEmulator.egg-info/requires.txt
TermEmulator.egg-info/top_level.txt
TermEmulator.egg-info/zip-safe