Metadata-Version: 1.0
Name: TermEmulator
Version: 1.0.2
Summary: Emulator for V100 terminal programs
Home-page: https://github.com/sivachandran/TermEmulator
Author: Siva Chandran P
Author-email: siva.chandran.p@gmail.com
License: LGPL
Platform: UNKNOWN
